<annotationInfo>
<item  id="208" filename="correlator.cpp" linenumber="225" name="tmp_1" contextFuncName="correlator" moduleName="correlator" rtlName="tmp_1_fu_470_p1" latency="0" BRAM="-1" DSP="-1" FF="-1" LUT="-1" fileDirectory="/home/alex/Documents/RFNoCFrameSynchHWAccel/correlatorDev"></item>
<item  id="514" filename="correlator.cpp" linenumber="238" name="tmp_2" contextFuncName="correlator" moduleName="correlator" rtlName="tmp_2_fu_1854_p3" latency="0" BRAM="-1" DSP="-1" FF="-1" LUT="-1" fileDirectory="/home/alex/Documents/RFNoCFrameSynchHWAccel/correlatorDev"></item>
<item  id="515" filename="correlator.cpp" linenumber="238" name="tmp_2_cast" contextFuncName="correlator" moduleName="correlator" rtlName="tmp_2_cast_fu_1862_p1" latency="0" BRAM="-1" DSP="-1" FF="-1" LUT="-1" fileDirectory="/home/alex/Documents/RFNoCFrameSynchHWAccel/correlatorDev"></item>
<item  id="516" filename="correlator.cpp" linenumber="238" name="tmp_71_2" contextFuncName="correlator" moduleName="correlator" rtlName="tmp_71_2_fu_1866_p3" latency="0" BRAM="-1" DSP="-1" FF="-1" LUT="-1" fileDirectory="/home/alex/Documents/RFNoCFrameSynchHWAccel/correlatorDev"></item>
<item  id="517" filename="correlator.cpp" linenumber="238" name="tmp_71_2_cast" contextFuncName="correlator" moduleName="correlator" rtlName="tmp_71_2_cast_fu_1874_p1" latency="0" BRAM="-1" DSP="-1" FF="-1" LUT="-1" fileDirectory="/home/alex/Documents/RFNoCFrameSynchHWAccel/correlatorDev"></item>
<item  id="518" filename="correlator.cpp" linenumber="238" name="tmp_71_5" contextFuncName="correlator" moduleName="correlator" rtlName="tmp_71_5_fu_1878_p3" latency="0" BRAM="-1" DSP="-1" FF="-1" LUT="-1" fileDirectory="/home/alex/Documents/RFNoCFrameSynchHWAccel/correlatorDev"></item>
<item  id="519" filename="correlator.cpp" linenumber="238" name="tmp_71_5_cast" contextFuncName="correlator" moduleName="correlator" rtlName="tmp_71_5_cast_fu_1886_p1" latency="0" BRAM="-1" DSP="-1" FF="-1" LUT="-1" fileDirectory="/home/alex/Documents/RFNoCFrameSynchHWAccel/correlatorDev"></item>
<item  id="520" filename="correlator.cpp" linenumber="238" name="tmp_71_7" contextFuncName="correlator" moduleName="correlator" rtlName="tmp_71_7_fu_1890_p3" latency="0" BRAM="-1" DSP="-1" FF="-1" LUT="-1" fileDirectory="/home/alex/Documents/RFNoCFrameSynchHWAccel/correlatorDev"></item>
<item  id="521" filename="correlator.cpp" linenumber="238" name="tmp_71_7_cast" contextFuncName="correlator" moduleName="correlator" rtlName="tmp_71_7_cast_fu_1898_p1" latency="0" BRAM="-1" DSP="-1" FF="-1" LUT="-1" fileDirectory="/home/alex/Documents/RFNoCFrameSynchHWAccel/correlatorDev"></item>
<item  id="530" filename="correlator.cpp" linenumber="238" name="tmp_71_s" contextFuncName="correlator" moduleName="correlator" rtlName="tmp_71_s_fu_1942_p3" latency="0" BRAM="-1" DSP="-1" FF="-1" LUT="-1" fileDirectory="/home/alex/Documents/RFNoCFrameSynchHWAccel/correlatorDev"></item>
<item  id="531" filename="correlator.cpp" linenumber="238" name="tmp_71_cast" contextFuncName="correlator" moduleName="correlator" rtlName="tmp_71_cast_fu_1950_p1" latency="0" BRAM="-1" DSP="-1" FF="-1" LUT="-1" fileDirectory="/home/alex/Documents/RFNoCFrameSynchHWAccel/correlatorDev"></item>
<item  id="534" filename="correlator.cpp" linenumber="238" name="tmp_71_1" contextFuncName="correlator" moduleName="correlator" rtlName="tmp_71_1_fu_1964_p3" latency="0" BRAM="-1" DSP="-1" FF="-1" LUT="-1" fileDirectory="/home/alex/Documents/RFNoCFrameSynchHWAccel/correlatorDev"></item>
<item  id="535" filename="correlator.cpp" linenumber="238" name="tmp_71_1_cast" contextFuncName="correlator" moduleName="correlator" rtlName="tmp_71_1_cast_fu_1972_p1" latency="0" BRAM="-1" DSP="-1" FF="-1" LUT="-1" fileDirectory="/home/alex/Documents/RFNoCFrameSynchHWAccel/correlatorDev"></item>
<item  id="538" filename="correlator.cpp" linenumber="238" name="tmp_71_3" contextFuncName="correlator" moduleName="correlator" rtlName="tmp_71_3_fu_1986_p3" latency="0" BRAM="-1" DSP="-1" FF="-1" LUT="-1" fileDirectory="/home/alex/Documents/RFNoCFrameSynchHWAccel/correlatorDev"></item>
<item  id="539" filename="correlator.cpp" linenumber="238" name="tmp_71_3_cast" contextFuncName="correlator" moduleName="correlator" rtlName="tmp_71_3_cast_fu_1994_p1" latency="0" BRAM="-1" DSP="-1" FF="-1" LUT="-1" fileDirectory="/home/alex/Documents/RFNoCFrameSynchHWAccel/correlatorDev"></item>
<item  id="542" filename="correlator.cpp" linenumber="238" name="tmp_71_4" contextFuncName="correlator" moduleName="correlator" rtlName="tmp_71_4_fu_2008_p3" latency="0" BRAM="-1" DSP="-1" FF="-1" LUT="-1" fileDirectory="/home/alex/Documents/RFNoCFrameSynchHWAccel/correlatorDev"></item>
<item  id="543" filename="correlator.cpp" linenumber="238" name="tmp_71_4_cast" contextFuncName="correlator" moduleName="correlator" rtlName="tmp_71_4_cast_fu_2015_p1" latency="0" BRAM="-1" DSP="-1" FF="-1" LUT="-1" fileDirectory="/home/alex/Documents/RFNoCFrameSynchHWAccel/correlatorDev"></item>
<item  id="544" filename="correlator.cpp" linenumber="238" name="tmp8" contextFuncName="correlator" moduleName="correlator" rtlName="tmp8_fu_2019_p2" latency="0" BRAM="-1" DSP="-1" FF="0" LUT="39" fileDirectory="/home/alex/Documents/RFNoCFrameSynchHWAccel/correlatorDev"></item>
<item  id="545" filename="correlator.cpp" linenumber="238" name="tmp9" contextFuncName="correlator" moduleName="correlator" rtlName="tmp9_fu_2025_p2" latency="0" BRAM="-1" DSP="-1" FF="0" LUT="29" fileDirectory="/home/alex/Documents/RFNoCFrameSynchHWAccel/correlatorDev"></item>
<item  id="546" filename="correlator.cpp" linenumber="238" name="tmp9_cast" contextFuncName="correlator" moduleName="correlator" rtlName="tmp9_cast_fu_2031_p1" latency="0" BRAM="-1" DSP="-1" FF="-1" LUT="-1" fileDirectory="/home/alex/Documents/RFNoCFrameSynchHWAccel/correlatorDev"></item>
<item  id="547" filename="correlator.cpp" linenumber="238" name="tmp7" contextFuncName="correlator" moduleName="correlator" rtlName="tmp7_fu_2035_p2" latency="0" BRAM="-1" DSP="-1" FF="0" LUT="32" fileDirectory="/home/alex/Documents/RFNoCFrameSynchHWAccel/correlatorDev"></item>
<item  id="548" filename="correlator.cpp" linenumber="238" name="tmp1" contextFuncName="correlator" moduleName="correlator" rtlName="tmp1_fu_2041_p2" latency="0" BRAM="-1" DSP="-1" FF="0" LUT="29" fileDirectory="/home/alex/Documents/RFNoCFrameSynchHWAccel/correlatorDev"></item>
<item  id="549" filename="correlator.cpp" linenumber="238" name="tmp11_cast" contextFuncName="correlator" moduleName="correlator" rtlName="tmp11_cast_fu_2047_p1" latency="0" BRAM="-1" DSP="-1" FF="-1" LUT="-1" fileDirectory="/home/alex/Documents/RFNoCFrameSynchHWAccel/correlatorDev"></item>
<item  id="550" filename="correlator.cpp" linenumber="238" name="tmp2" contextFuncName="correlator" moduleName="correlator" rtlName="tmp2_fu_2051_p2" latency="0" BRAM="-1" DSP="-1" FF="0" LUT="29" fileDirectory="/home/alex/Documents/RFNoCFrameSynchHWAccel/correlatorDev"></item>
<item  id="551" filename="correlator.cpp" linenumber="238" name="tmp13_cast" contextFuncName="correlator" moduleName="correlator" rtlName="tmp13_cast_fu_2057_p1" latency="0" BRAM="-1" DSP="-1" FF="-1" LUT="-1" fileDirectory="/home/alex/Documents/RFNoCFrameSynchHWAccel/correlatorDev"></item>
<item  id="552" filename="correlator.cpp" linenumber="238" name="tmp3" contextFuncName="correlator" moduleName="correlator" rtlName="tmp3_fu_2061_p2" latency="0" BRAM="-1" DSP="-1" FF="0" LUT="30" fileDirectory="/home/alex/Documents/RFNoCFrameSynchHWAccel/correlatorDev"></item>
<item  id="553" filename="correlator.cpp" linenumber="238" name="tmp12_cast" contextFuncName="correlator" moduleName="correlator" rtlName="tmp12_cast_fu_2067_p1" latency="0" BRAM="-1" DSP="-1" FF="-1" LUT="-1" fileDirectory="/home/alex/Documents/RFNoCFrameSynchHWAccel/correlatorDev"></item>
<item  id="554" filename="correlator.cpp" linenumber="238" name="tmp4" contextFuncName="correlator" moduleName="correlator" rtlName="tmp4_fu_2071_p2" latency="0" BRAM="-1" DSP="-1" FF="0" LUT="31" fileDirectory="/home/alex/Documents/RFNoCFrameSynchHWAccel/correlatorDev"></item>
<item  id="555" filename="correlator.cpp" linenumber="238" name="tmp10_cast" contextFuncName="correlator" moduleName="correlator" rtlName="tmp10_cast_fu_2077_p1" latency="0" BRAM="-1" DSP="-1" FF="-1" LUT="-1" fileDirectory="/home/alex/Documents/RFNoCFrameSynchHWAccel/correlatorDev"></item>
<item  id="556" filename="correlator.cpp" linenumber="238" name="loc_V" contextFuncName="correlator" moduleName="correlator" rtlName="loc_V_fu_2081_p2" latency="0" BRAM="-1" DSP="-1" FF="0" LUT="32" fileDirectory="/home/alex/Documents/RFNoCFrameSynchHWAccel/correlatorDev"></item>
<item  id="563" filename="correlator.cpp" linenumber="371" name="tmp_s" contextFuncName="correlator" moduleName="correlator" rtlName="tmp_s_fu_2104_p2" latency="0" BRAM="-1" DSP="-1" FF="0" LUT="39" fileDirectory="/home/alex/Documents/RFNoCFrameSynchHWAccel/correlatorDev"></item>
</annotationInfo>
